<?xml version="1.0" encoding="utf-8" ?><dwsync><file name="3d_pie_banner.png" server="ftp.ekingmg.com" local="3522407222" remote="3523486800" Dst="-1" /><file name="Above & Beyond Banner new portal.jpg" server="ftp.ekingmg.com" local="3487264852" remote="3523486800" Dst="-1" /><file name="capbuild-thumb.png" server="ftp.ekingmg.com" local="3522598122" remote="3523486800" Dst="-1" /><file name="capbuild.png" server="ftp.ekingmg.com" local="3522598091" remote="3523486800" Dst="-1" /><file name="Carousel_Placeholder.png" server="ftp.ekingmg.com" local="3522083158" remote="3523486800" Dst="-1" /><file name="DISHMAS-POSTER-thumb.png" server="ftp.ekingmg.com" local="3522592413" remote="3523486800" Dst="-1" /><file name="DISHMAS-POSTER.png" server="ftp.ekingmg.com" local="3522592384" remote="3523486800" Dst="-1" /><file name="Earth-Day-Banner.jpg" server="ftp.ekingmg.com" local="3512492210" remote="3523486800" Dst="-1" /><file name="ERIC_KING_WHITE_TEXT.png" server="ftp.ekingmg.com" local="3524923924" remote="3524939580" Dst="-1" /><file name="exp-of-a-lifetime-thumb.png" server="ftp.ekingmg.com" local="3522590771" remote="3523486800" Dst="-1" /><file name="exp-of-a-lifetime.png" server="ftp.ekingmg.com" local="3522590738" remote="3523486800" Dst="-1" /><file name="ihsconfroom_desktop.jpg" server="ftp.ekingmg.com" local="3508161322" remote="3523486800" Dst="-1" /><file name="ihsconfroom_desktop_750.png" server="ftp.ekingmg.com" local="3522507445" remote="3523486800" Dst="-1" /><file name="ihsconfroom_desktop_thumb.png" server="ftp.ekingmg.com" local="3522506668" remote="3523486800" Dst="-1" /><file name="ImgResponsive_Placeholder.png" server="ftp.ekingmg.com" local="3522083158" remote="3523486800" Dst="-1" /><file name="mothers-day-banner.png" server="ftp.ekingmg.com" local="3522264832" remote="3523486800" Dst="-1" /><file name="nba-finals-banner.jpg" server="ftp.ekingmg.com" local="3516384420" remote="3523486800" Dst="-1" /><file name="NHL-Finals-Banner.jpg" server="ftp.ekingmg.com" local="3516386356" remote="3523486800" Dst="-1" /><file name="photo_logo-thumb.png" server="ftp.ekingmg.com" local="3522606877" remote="3523486800" Dst="-1" /><file name="photo_logo.png" server="ftp.ekingmg.com" local="3522606860" remote="3523486800" Dst="-1" /><file name="shs-holiday.png" server="ftp.ekingmg.com" local="3522157558" remote="3523486800" Dst="-1" /><file name="SHS-live-banner.png" server="ftp.ekingmg.com" local="3522157516" remote="3523486800" Dst="-1" /><file name="SlingTV-banner.jpg" server="ftp.ekingmg.com" local="3509473020" remote="3523486800" Dst="-1" /><file name="tech-track-logo-800.png" server="ftp.ekingmg.com" local="3522587712" remote="3523486800" Dst="-1" /><file name="tech-track-logo-thumb.png" server="ftp.ekingmg.com" local="3522587732" remote="3523486800" Dst="-1" /><file name="UFC-anouncement-banner.jpg" server="ftp.ekingmg.com" local="3508161098" remote="3523486800" Dst="-1" /><file name="UFC-March-Madness-thumb.png" server="ftp.ekingmg.com" local="3522606125" remote="3523486800" Dst="-1" /><file name="UFC-March-Madness.png" server="ftp.ekingmg.com" local="3522606064" remote="3523486860" Dst="-1" /><file name="wanted_sign.jpg" server="ftp.ekingmg.com" local="3522524300" remote="3523486860" Dst="-1" /><file name="wanted_sign_900.png" server="ftp.ekingmg.com" local="3522524297" remote="3523486860" Dst="-1" /><file name="wanted_sign_thumb.png" server="ftp.ekingmg.com" local="3522524258" remote="3523486860" Dst="-1" /><file name="whitepattern.jpg" server="ftp.ekingmg.com" local="3522172990" remote="3523486860" Dst="-1" /><file name="xmasbanner.png" server="ftp.ekingmg.com" local="3522326724" remote="3523486860" Dst="-1" /><file name="G_image.jpg" server="ftp.ekingmg.com" local="3503588612" remote="3523486800" Dst="-1" /><file name="heat_banner.png" server="ftp.ekingmg.com" local="3522264996" remote="3523744260" Dst="-1" /><file name="DBPS_Cover.png" server="ftp.ekingmg.com" local="3524166620" remote="3524175660" Dst="-1" /><file name="DBPS_Cover_thumb.png" server="ftp.ekingmg.com" local="3524166638" remote="3524175660" Dst="-1" /><file name="qas-logo-final-thumb.png" server="ftp.ekingmg.com" local="3524166440" remote="3524175660" Dst="-1" /><file name="qas-logo-final.png" server="ftp.ekingmg.com" local="3524166292" remote="3524175660" Dst="-1" /><file name="stills.png" server="ftp.ekingmg.com" local="3584033553" remote="3584040780" Dst="-1" /><file name="eric_behind_camera_1.png" server="ftp.ekingmg.com" local="3525898209" remote="3525907740" Dst="-1" /><file name="interior_render.png" server="ftp.ekingmg.com" local="3532805862" remote="3532813620" Dst="-1" /><file name="interior_render_thumb.png" server="ftp.ekingmg.com" local="3532805960" remote="3532813620" Dst="-1" /><file name="Tool_Mat.jpg" server="ftp.ekingmg.com" local="3584034133" remote="3584121360" Dst="-1" /><file name="Tool_Mat_thumb.jpg" server="ftp.ekingmg.com" local="3584034219" remote="3584121360" Dst="-1" /><file name="bathroom_render_forweb.png" server="ftp.ekingmg.com" local="3586711010" remote="3586718580" Dst="-1" /><file name="bathroom_render_forwebthumb.png" server="ftp.ekingmg.com" local="3586711222" remote="3586718580" Dst="-1" /></dwsync>